LICENSE
MANIFEST.in
README
cumulus-bundle-handler
setup.py
cumulus_bundle_handler/__init__.py
cumulus_bundle_handler/bundle_manager.py
cumulus_bundle_handler/command_line_options.py
cumulus_bundle_handler/config.py
cumulus_bundle_handler/script_executor.py
cumulus_bundle_handler/settings.conf
cumulus_bundle_handler.egg-info/PKG-INFO
cumulus_bundle_handler.egg-info/SOURCES.txt
cumulus_bundle_handler.egg-info/dependency_links.txt
cumulus_bundle_handler.egg-info/not-zip-safe
cumulus_bundle_handler.egg-info/requires.txt
cumulus_bundle_handler.egg-info/top_level.txt