Metadata-Version: 1.1
Name: cumulus-bundle-handler
Version: 1.0.0
Summary: Cumulus AWS deployment tools
Home-page: http://www.skymillsolutions.com
Author: Sebastian Dahlgren
Author-email: sebastian.dahlgren@skymill.se
License: Proprietary
Keywords: cumulus cloudformation amazon web services
Platform: Any
Classifier: Development Status :: 4 - Beta
Classifier: Environment :: Console
Classifier: License :: OSI Approved :: Apache Software License
Classifier: Operating System :: OS Independent
Classifier: Programming Language :: Python
